_openmmtorch.cpython-313-darwin.so
openmmtorch.py
OpenMM.libs/lib/libOpenMMTorch.dylib
OpenMM.libs/lib/plugins/libOpenMMTorchReference.dylib
OpenMM.libs/lib/plugins/libOpenMMTorchOpenCL.dylib
openmmtorch-1.5.dist-info/RECORD
openmmtorch-1.5.dist-info/WHEEL
openmmtorch-1.5.dist-info/top_level.txt
openmmtorch-1.5.dist-info/METADATA
