Metadata-Version: 2.4
Name: openmmtorch
Version: 1.5
Requires-Dist: openmm
Requires-Dist: torch
Provides-Extra: cuda12
Requires-Dist: OpenMM-Torch-CUDA-12==1.5; extra == "cuda12"
Provides-Extra: cuda13
Requires-Dist: OpenMM-Torch-CUDA-13==1.5; extra == "cuda13"
Provides-Extra: hip6
Requires-Dist: OpenMM-Torch-HIP-6==1.5; extra == "hip6"
Provides-Extra: hip7
Requires-Dist: OpenMM-Torch-HIP-7==1.5; extra == "hip7"
Dynamic: provides-extra
Dynamic: requires-dist
